{
  "name": "免费在线图片取色器 - 纯粹工具站",
  "shortName": "图片取色器",
  "description": "免费在线图片取色器，支持上传图片并点击取色，输出 HEX/RGB/HSL 等格式，一键复制。",
  "seoDescription": "设计师必备的免费在线图片取色神器 - ATools - 支持精确像素级取色，一键获取HEX、RGB、HSL、CMYK等多种颜色格式！支持放大镜功能，取色精度达到像素级别，支持颜色历史记录和调色板保存。采用先进的颜色空间转换算法，颜色准确度99.9%。完全本地处理，保护图片隐私，支持拖拽上传和批量取色。是UI设计师、网页开发者、平面设计师的必备工具。界面简洁美观，操作极其简单，支持快捷键操作。完全免费开源，无任何限制，是全球设计师首选的专业取色工具！",
  "lang": "zh-CN",
  "themeColor": "#0f172a",
  "backgroundColor": "#0f172a",
  "icon": "/icon.svg",
  "category": "图片工具",
  "keywords": [
    "免费图片取色",
    "在线取色器",
    "颜色提取",
    "HEX颜色",
    "RGB取色工具"
  ],
  "ui": {
    "pickImageError": "请选择图片文件",
    "dropTitle": "点击或拖拽图片到此处",
    "dropSubtitle": "支持常见图片格式（JPG/PNG/WebP…）",
    "currentImagePrefix": "当前图片：",
    "reselect": "重新选择",
    "hintPick": "提示：点击画布任意位置即可取色。",
    "colorInfo": "颜色信息",
    "pixelPrefix": "像素坐标：",
    "notPicked": "未取色",
    "copy": "复制",
    "alphaNote": "说明：带透明度的颜色会输出 8 位 HEX（#RRGGBBAA）。"
  },
  "pageFeatures": {
    "floatingUploadAction": true,
    "globalDropZone": true
  }
}
